Metadata-Version: 2.1
Name: snfatigue
Version: 0.0.1
Summary: SN fatigue calculations
Home-page: https://github.com/haphaeu/snfatigue
Author: Rafael Rossi
License: GPL2
Platform: UNKNOWN
Requires-Python: >=3.6, <4
Provides-Extra: dev
